[
  {
    "content_id": 284909,
    "reference_id": 1527,
    "version": "1.0.0",
    "title": "Ibex",
    "media_type": "Image",
    "index_reference": "ibex",
    "language": "zlm",
    "content": "<h3>Image Content</h3>\n<block>\n<p><img src='https://cdn.aquifer.bible/aquifer-content/resources/Media/WEB-0313_ibex.jpg' alt='Image' /></p>\n<p><a href='https://cdn.aquifer.bible/aquifer-content/resources/Media/WEB-0313_ibex.jpg'>link</a></p>\n</block>",
    "associations": {
      "passage": [
        {
          "start_ref": "05014005",
          "start_ref_usfm": "DEU 14:5",
          "end_ref": "05014005",
          "end_ref_usfm": "DEU 14:5"
        },
        {
          "start_ref": "18039001",
          "start_ref_usfm": "JOB 39:1",
          "end_ref": "18039001",
          "end_ref_usfm": "JOB 39:1"
        },
        {
          "start_ref": "19104018",
          "start_ref_usfm": "PSA 104:18",
          "end_ref": "19104018",
          "end_ref_usfm": "PSA 104:18"
        },
        {
          "start_ref": "20005019",
          "start_ref_usfm": "PRO 5:19",
          "end_ref": "20005019",
          "end_ref_usfm": "PRO 5:19"
        }
      ],
      "resource": []
    }
  }
]