[
  {
    "content_id": 282328,
    "reference_id": 1745,
    "version": "1.0.0",
    "title": "Tissage",
    "media_type": "Image",
    "index_reference": "tissage",
    "language": "fra",
    "content": "<h3>Image Content</h3>\n<block>\n<p><img src='https://cdn.aquifer.bible/aquifer-content/resources/Media/WEB-0347_weaving.jpg' alt='Image' /></p>\n<p><a href='https://cdn.aquifer.bible/aquifer-content/resources/Media/WEB-0347_weaving.jpg'>link</a></p>\n</block>",
    "associations": {
      "passage": [
        {
          "start_ref": "03013048",
          "start_ref_usfm": "LEV 13:48",
          "end_ref": "03013048",
          "end_ref_usfm": "LEV 13:48"
        },
        {
          "start_ref": "03013049",
          "start_ref_usfm": "LEV 13:49",
          "end_ref": "03013049",
          "end_ref_usfm": "LEV 13:49"
        },
        {
          "start_ref": "03013051",
          "start_ref_usfm": "LEV 13:51",
          "end_ref": "03013051",
          "end_ref_usfm": "LEV 13:51"
        },
        {
          "start_ref": "03013052",
          "start_ref_usfm": "LEV 13:52",
          "end_ref": "03013052",
          "end_ref_usfm": "LEV 13:52"
        },
        {
          "start_ref": "03013053",
          "start_ref_usfm": "LEV 13:53",
          "end_ref": "03013053",
          "end_ref_usfm": "LEV 13:53"
        },
        {
          "start_ref": "03013056",
          "start_ref_usfm": "LEV 13:56",
          "end_ref": "03013056",
          "end_ref_usfm": "LEV 13:56"
        },
        {
          "start_ref": "03013057",
          "start_ref_usfm": "LEV 13:57",
          "end_ref": "03013057",
          "end_ref_usfm": "LEV 13:57"
        },
        {
          "start_ref": "03013058",
          "start_ref_usfm": "LEV 13:58",
          "end_ref": "03013058",
          "end_ref_usfm": "LEV 13:58"
        },
        {
          "start_ref": "03013059",
          "start_ref_usfm": "LEV 13:59",
          "end_ref": "03013059",
          "end_ref_usfm": "LEV 13:59"
        },
        {
          "start_ref": "23038012",
          "start_ref_usfm": "ISA 38:12",
          "end_ref": "23038012",
          "end_ref_usfm": "ISA 38:12"
        }
      ],
      "resource": []
    }
  }
]