[
  {
    "content_id": 289611,
    "reference_id": 1564,
    "version": "1.0.0",
    "title": "Hoopoe",
    "media_type": "Image",
    "index_reference": "hoopoe",
    "language": "hau",
    "content": "<h3>Image Content</h3>\n<block>\n<p><img src='https://cdn.aquifer.bible/aquifer-content/resources/Media/WEB-0301_hoopoe.jpg' alt='Image' /></p>\n<p><a href='https://cdn.aquifer.bible/aquifer-content/resources/Media/WEB-0301_hoopoe.jpg'>link</a></p>\n</block>",
    "associations": {
      "passage": [
        {
          "start_ref": "03011019",
          "start_ref_usfm": "LEV 11:19",
          "end_ref": "03011019",
          "end_ref_usfm": "LEV 11:19"
        },
        {
          "start_ref": "05014018",
          "start_ref_usfm": "DEU 14:18",
          "end_ref": "05014018",
          "end_ref_usfm": "DEU 14:18"
        }
      ],
      "resource": []
    }
  }
]