[
  {
    "content_id": 3240,
    "reference_id": 2408,
    "title": "Assorted Jewelry",
    "media_type": "Image",
    "index_reference": "assorted jewelry",
    "language": "eng",
    "content": "<h3>Image Content</h3>\n<block>\n<p><img src='https://cdn.aquifer.bible/aquifer-content/resources/Media/WEB-0530_assorted_jewelry.jpg' alt='Image' /></p>\n<p><a href='https://cdn.aquifer.bible/aquifer-content/resources/Media/WEB-0530_assorted_jewelry.jpg'>link</a></p>\n</block>",
    "associations": {
      "passage": [
        {
          "start_ref": "01024053",
          "start_ref_usfm": "GEN 24:53",
          "end_ref": "01024053",
          "end_ref_usfm": "GEN 24:53"
        },
        {
          "start_ref": "02003022",
          "start_ref_usfm": "EXO 3:22",
          "end_ref": "02003022",
          "end_ref_usfm": "EXO 3:22"
        },
        {
          "start_ref": "02011002",
          "start_ref_usfm": "EXO 11:2",
          "end_ref": "02011002",
          "end_ref_usfm": "EXO 11:2"
        },
        {
          "start_ref": "02012035",
          "start_ref_usfm": "EXO 12:35",
          "end_ref": "02012035",
          "end_ref_usfm": "EXO 12:35"
        },
        {
          "start_ref": "02033004",
          "start_ref_usfm": "EXO 33:4",
          "end_ref": "02033004",
          "end_ref_usfm": "EXO 33:4"
        },
        {
          "start_ref": "02033005",
          "start_ref_usfm": "EXO 33:5",
          "end_ref": "02033005",
          "end_ref_usfm": "EXO 33:5"
        },
        {
          "start_ref": "02033006",
          "start_ref_usfm": "EXO 33:6",
          "end_ref": "02033006",
          "end_ref_usfm": "EXO 33:6"
        },
        {
          "start_ref": "02035022",
          "start_ref_usfm": "EXO 35:22",
          "end_ref": "02035022",
          "end_ref_usfm": "EXO 35:22"
        },
        {
          "start_ref": "04031050",
          "start_ref_usfm": "NUM 31:50",
          "end_ref": "04031050",
          "end_ref_usfm": "NUM 31:50"
        },
        {
          "start_ref": "04031051",
          "start_ref_usfm": "NUM 31:51",
          "end_ref": "04031051",
          "end_ref_usfm": "NUM 31:51"
        },
        {
          "start_ref": "10001024",
          "start_ref_usfm": "2SA 1:24",
          "end_ref": "10001024",
          "end_ref_usfm": "2SA 1:24"
        },
        {
          "start_ref": "12012014",
          "start_ref_usfm": "2KI 12:14",
          "end_ref": "12012014",
          "end_ref_usfm": "2KI 12:14"
        },
        {
          "start_ref": "20025012",
          "start_ref_usfm": "PRO 25:12",
          "end_ref": "20025012",
          "end_ref_usfm": "PRO 25:12"
        },
        {
          "start_ref": "22001010",
          "start_ref_usfm": "SNG 1:10",
          "end_ref": "22001010",
          "end_ref_usfm": "SNG 1:10"
        },
        {
          "start_ref": "22001011",
          "start_ref_usfm": "SNG 1:11",
          "end_ref": "22001011",
          "end_ref_usfm": "SNG 1:11"
        },
        {
          "start_ref": "22007002",
          "start_ref_usfm": "SNG 7:2",
          "end_ref": "22007002",
          "end_ref_usfm": "SNG 7:2"
        },
        {
          "start_ref": "23049018",
          "start_ref_usfm": "ISA 49:18",
          "end_ref": "23049018",
          "end_ref_usfm": "ISA 49:18"
        },
        {
          "start_ref": "23061010",
          "start_ref_usfm": "ISA 61:10",
          "end_ref": "23061010",
          "end_ref_usfm": "ISA 61:10"
        },
        {
          "start_ref": "24002032",
          "start_ref_usfm": "JER 2:32",
          "end_ref": "24002032",
          "end_ref_usfm": "JER 2:32"
        },
        {
          "start_ref": "24004030",
          "start_ref_usfm": "JER 4:30",
          "end_ref": "24004030",
          "end_ref_usfm": "JER 4:30"
        },
        {
          "start_ref": "26007020",
          "start_ref_usfm": "EZK 7:20",
          "end_ref": "26007020",
          "end_ref_usfm": "EZK 7:20"
        },
        {
          "start_ref": "26016011",
          "start_ref_usfm": "EZK 16:11",
          "end_ref": "26016011",
          "end_ref_usfm": "EZK 16:11"
        },
        {
          "start_ref": "26016017",
          "start_ref_usfm": "EZK 16:17",
          "end_ref": "26016017",
          "end_ref_usfm": "EZK 16:17"
        },
        {
          "start_ref": "26016039",
          "start_ref_usfm": "EZK 16:39",
          "end_ref": "26016039",
          "end_ref_usfm": "EZK 16:39"
        },
        {
          "start_ref": "26023026",
          "start_ref_usfm": "EZK 23:26",
          "end_ref": "26023026",
          "end_ref_usfm": "EZK 23:26"
        },
        {
          "start_ref": "26023040",
          "start_ref_usfm": "EZK 23:40",
          "end_ref": "26023040",
          "end_ref_usfm": "EZK 23:40"
        },
        {
          "start_ref": "28002015",
          "start_ref_usfm": "HOS 2:15",
          "end_ref": "28002015",
          "end_ref_usfm": "HOS 2:15"
        },
        {
          "start_ref": "54002009",
          "start_ref_usfm": "1TI 2:9",
          "end_ref": "54002009",
          "end_ref_usfm": "1TI 2:9"
        },
        {
          "start_ref": "60003003",
          "start_ref_usfm": "1PE 3:3",
          "end_ref": "60003003",
          "end_ref_usfm": "1PE 3:3"
        },
        {
          "start_ref": "66017004",
          "start_ref_usfm": "REV 17:4",
          "end_ref": "66017004",
          "end_ref_usfm": "REV 17:4"
        },
        {
          "start_ref": "66018016",
          "start_ref_usfm": "REV 18:16",
          "end_ref": "66018016",
          "end_ref_usfm": "REV 18:16"
        }
      ],
      "resource": []
    }
  }
]