[
  {
    "content_id": 2592,
    "reference_id": 1760,
    "version": "1.0.0",
    "title": "Leg Protectors Roman",
    "media_type": "Image",
    "index_reference": "leg protectors roman",
    "language": "eng",
    "content": "<h3>Image Content</h3>\n<block>\n<p><img src='https://cdn.aquifer.bible/aquifer-content/resources/Media/WEB-0388_leg_protectors_roman.jpg' alt='Image' /></p>\n<p><a href='https://cdn.aquifer.bible/aquifer-content/resources/Media/WEB-0388_leg_protectors_roman.jpg'>link</a></p>\n</block>",
    "associations": {
      "passage": [
        {
          "start_ref": "09017006",
          "start_ref_usfm": "1SA 17:6",
          "end_ref": "09017006",
          "end_ref_usfm": "1SA 17:6"
        }
      ],
      "resource": []
    }
  }
]