[
  {
    "content_id": 295695,
    "reference_id": 2049,
    "version": "1.0.0",
    "title": "軛牛",
    "media_type": "Image",
    "index_reference": "軛牛",
    "language": "zht",
    "content": "<h3>Image Content</h3>\n<block>\n<p><img src='https://cdn.aquifer.bible/aquifer-content/resources/Media/WEB-0927_yoke_bullock.jpg' alt='Image' /></p>\n<p><a href='https://cdn.aquifer.bible/aquifer-content/resources/Media/WEB-0927_yoke_bullock.jpg'>link</a></p>\n</block>",
    "associations": {
      "passage": [
        {
          "start_ref": "01027040",
          "start_ref_usfm": "GEN 27:40",
          "end_ref": "01027040",
          "end_ref_usfm": "GEN 27:40"
        },
        {
          "start_ref": "03026013",
          "start_ref_usfm": "LEV 26:13",
          "end_ref": "03026013",
          "end_ref_usfm": "LEV 26:13"
        },
        {
          "start_ref": "04019002",
          "start_ref_usfm": "NUM 19:2",
          "end_ref": "04019002",
          "end_ref_usfm": "NUM 19:2"
        },
        {
          "start_ref": "05021003",
          "start_ref_usfm": "DEU 21:3",
          "end_ref": "05021003",
          "end_ref_usfm": "DEU 21:3"
        },
        {
          "start_ref": "05028048",
          "start_ref_usfm": "DEU 28:48",
          "end_ref": "05028048",
          "end_ref_usfm": "DEU 28:48"
        },
        {
          "start_ref": "09006007",
          "start_ref_usfm": "1SA 6:7",
          "end_ref": "09006007",
          "end_ref_usfm": "1SA 6:7"
        },
        {
          "start_ref": "11012004",
          "start_ref_usfm": "1KI 12:4",
          "end_ref": "11012004",
          "end_ref_usfm": "1KI 12:4"
        },
        {
          "start_ref": "11012009",
          "start_ref_usfm": "1KI 12:9",
          "end_ref": "11012009",
          "end_ref_usfm": "1KI 12:9"
        },
        {
          "start_ref": "11012010",
          "start_ref_usfm": "1KI 12:10",
          "end_ref": "11012010",
          "end_ref_usfm": "1KI 12:10"
        },
        {
          "start_ref": "11012011",
          "start_ref_usfm": "1KI 12:11",
          "end_ref": "11012011",
          "end_ref_usfm": "1KI 12:11"
        },
        {
          "start_ref": "11012014",
          "start_ref_usfm": "1KI 12:14",
          "end_ref": "11012014",
          "end_ref_usfm": "1KI 12:14"
        },
        {
          "start_ref": "14010004",
          "start_ref_usfm": "2CH 10:4",
          "end_ref": "14010004",
          "end_ref_usfm": "2CH 10:4"
        },
        {
          "start_ref": "14010009",
          "start_ref_usfm": "2CH 10:9",
          "end_ref": "14010009",
          "end_ref_usfm": "2CH 10:9"
        },
        {
          "start_ref": "14010010",
          "start_ref_usfm": "2CH 10:10",
          "end_ref": "14010010",
          "end_ref_usfm": "2CH 10:10"
        },
        {
          "start_ref": "14010011",
          "start_ref_usfm": "2CH 10:11",
          "end_ref": "14010011",
          "end_ref_usfm": "2CH 10:11"
        },
        {
          "start_ref": "14010014",
          "start_ref_usfm": "2CH 10:14",
          "end_ref": "14010014",
          "end_ref_usfm": "2CH 10:14"
        },
        {
          "start_ref": "23009003",
          "start_ref_usfm": "ISA 9:3",
          "end_ref": "23009003",
          "end_ref_usfm": "ISA 9:3"
        },
        {
          "start_ref": "23010027",
          "start_ref_usfm": "ISA 10:27",
          "end_ref": "23010027",
          "end_ref_usfm": "ISA 10:27"
        },
        {
          "start_ref": "23014025",
          "start_ref_usfm": "ISA 14:25",
          "end_ref": "23014025",
          "end_ref_usfm": "ISA 14:25"
        },
        {
          "start_ref": "23047006",
          "start_ref_usfm": "ISA 47:6",
          "end_ref": "23047006",
          "end_ref_usfm": "ISA 47:6"
        },
        {
          "start_ref": "23058006",
          "start_ref_usfm": "ISA 58:6",
          "end_ref": "23058006",
          "end_ref_usfm": "ISA 58:6"
        },
        {
          "start_ref": "23058009",
          "start_ref_usfm": "ISA 58:9",
          "end_ref": "23058009",
          "end_ref_usfm": "ISA 58:9"
        },
        {
          "start_ref": "24002020",
          "start_ref_usfm": "JER 2:20",
          "end_ref": "24002020",
          "end_ref_usfm": "JER 2:20"
        },
        {
          "start_ref": "24005005",
          "start_ref_usfm": "JER 5:5",
          "end_ref": "24005005",
          "end_ref_usfm": "JER 5:5"
        },
        {
          "start_ref": "24027002",
          "start_ref_usfm": "JER 27:2",
          "end_ref": "24027002",
          "end_ref_usfm": "JER 27:2"
        },
        {
          "start_ref": "24027008",
          "start_ref_usfm": "JER 27:8",
          "end_ref": "24027008",
          "end_ref_usfm": "JER 27:8"
        },
        {
          "start_ref": "24027011",
          "start_ref_usfm": "JER 27:11",
          "end_ref": "24027011",
          "end_ref_usfm": "JER 27:11"
        },
        {
          "start_ref": "24027012",
          "start_ref_usfm": "JER 27:12",
          "end_ref": "24027012",
          "end_ref_usfm": "JER 27:12"
        },
        {
          "start_ref": "24028002",
          "start_ref_usfm": "JER 28:2",
          "end_ref": "24028002",
          "end_ref_usfm": "JER 28:2"
        },
        {
          "start_ref": "24028004",
          "start_ref_usfm": "JER 28:4",
          "end_ref": "24028004",
          "end_ref_usfm": "JER 28:4"
        },
        {
          "start_ref": "24028010",
          "start_ref_usfm": "JER 28:10",
          "end_ref": "24028010",
          "end_ref_usfm": "JER 28:10"
        },
        {
          "start_ref": "24028011",
          "start_ref_usfm": "JER 28:11",
          "end_ref": "24028011",
          "end_ref_usfm": "JER 28:11"
        },
        {
          "start_ref": "24028012",
          "start_ref_usfm": "JER 28:12",
          "end_ref": "24028012",
          "end_ref_usfm": "JER 28:12"
        },
        {
          "start_ref": "24028013",
          "start_ref_usfm": "JER 28:13",
          "end_ref": "24028013",
          "end_ref_usfm": "JER 28:13"
        },
        {
          "start_ref": "24028014",
          "start_ref_usfm": "JER 28:14",
          "end_ref": "24028014",
          "end_ref_usfm": "JER 28:14"
        },
        {
          "start_ref": "24030008",
          "start_ref_usfm": "JER 30:8",
          "end_ref": "24030008",
          "end_ref_usfm": "JER 30:8"
        },
        {
          "start_ref": "25001014",
          "start_ref_usfm": "LAM 1:14",
          "end_ref": "25001014",
          "end_ref_usfm": "LAM 1:14"
        },
        {
          "start_ref": "25003027",
          "start_ref_usfm": "LAM 3:27",
          "end_ref": "25003027",
          "end_ref_usfm": "LAM 3:27"
        },
        {
          "start_ref": "26030018",
          "start_ref_usfm": "EZK 30:18",
          "end_ref": "26030018",
          "end_ref_usfm": "EZK 30:18"
        },
        {
          "start_ref": "26034027",
          "start_ref_usfm": "EZK 34:27",
          "end_ref": "26034027",
          "end_ref_usfm": "EZK 34:27"
        },
        {
          "start_ref": "28011004",
          "start_ref_usfm": "HOS 11:4",
          "end_ref": "28011004",
          "end_ref_usfm": "HOS 11:4"
        },
        {
          "start_ref": "34001013",
          "start_ref_usfm": "NAM 1:13",
          "end_ref": "34001013",
          "end_ref_usfm": "NAM 1:13"
        },
        {
          "start_ref": "40011029",
          "start_ref_usfm": "MAT 11:29",
          "end_ref": "40011029",
          "end_ref_usfm": "MAT 11:29"
        },
        {
          "start_ref": "40011030",
          "start_ref_usfm": "MAT 11:30",
          "end_ref": "40011030",
          "end_ref_usfm": "MAT 11:30"
        },
        {
          "start_ref": "44015010",
          "start_ref_usfm": "ACT 15:10",
          "end_ref": "44015010",
          "end_ref_usfm": "ACT 15:10"
        },
        {
          "start_ref": "47006014",
          "start_ref_usfm": "2CO 6:14",
          "end_ref": "47006014",
          "end_ref_usfm": "2CO 6:14"
        },
        {
          "start_ref": "48005001",
          "start_ref_usfm": "GAL 5:1",
          "end_ref": "48005001",
          "end_ref_usfm": "GAL 5:1"
        },
        {
          "start_ref": "54006001",
          "start_ref_usfm": "1TI 6:1",
          "end_ref": "54006001",
          "end_ref_usfm": "1TI 6:1"
        }
      ],
      "resource": []
    }
  }
]