[
  {
    "content_id": 284099,
    "reference_id": 1650,
    "title": "Kepala Sorgum",
    "media_type": "Image",
    "index_reference": "kepala sorgum",
    "language": "ind",
    "content": "<h3>Image Content</h3>\n<block>\n<p><img src='https://cdn.aquifer.bible/aquifer-content/resources/Media/WEB-0823_sorghum_head.jpg' alt='Image' /></p>\n<p><a href='https://cdn.aquifer.bible/aquifer-content/resources/Media/WEB-0823_sorghum_head.jpg'>link</a></p>\n</block>",
    "associations": {
      "passage": [
        {
          "start_ref": "01004003",
          "start_ref_usfm": "GEN 4:3",
          "end_ref": "01004003",
          "end_ref_usfm": "GEN 4:3"
        },
        {
          "start_ref": "03025019",
          "start_ref_usfm": "LEV 25:19",
          "end_ref": "03025019",
          "end_ref_usfm": "LEV 25:19"
        },
        {
          "start_ref": "04013020",
          "start_ref_usfm": "NUM 13:20",
          "end_ref": "04013020",
          "end_ref_usfm": "NUM 13:20"
        },
        {
          "start_ref": "04013026",
          "start_ref_usfm": "NUM 13:26",
          "end_ref": "04013026",
          "end_ref_usfm": "NUM 13:26"
        },
        {
          "start_ref": "04013027",
          "start_ref_usfm": "NUM 13:27",
          "end_ref": "04013027",
          "end_ref_usfm": "NUM 13:27"
        },
        {
          "start_ref": "05001025",
          "start_ref_usfm": "DEU 1:25",
          "end_ref": "05001025",
          "end_ref_usfm": "DEU 1:25"
        },
        {
          "start_ref": "05007013",
          "start_ref_usfm": "DEU 7:13",
          "end_ref": "05007013",
          "end_ref_usfm": "DEU 7:13"
        },
        {
          "start_ref": "05026002",
          "start_ref_usfm": "DEU 26:2",
          "end_ref": "05026002",
          "end_ref_usfm": "DEU 26:2"
        },
        {
          "start_ref": "05026010",
          "start_ref_usfm": "DEU 26:10",
          "end_ref": "05026010",
          "end_ref_usfm": "DEU 26:10"
        },
        {
          "start_ref": "05028004",
          "start_ref_usfm": "DEU 28:4",
          "end_ref": "05028004",
          "end_ref_usfm": "DEU 28:4"
        },
        {
          "start_ref": "05028011",
          "start_ref_usfm": "DEU 28:11",
          "end_ref": "05028011",
          "end_ref_usfm": "DEU 28:11"
        },
        {
          "start_ref": "05028018",
          "start_ref_usfm": "DEU 28:18",
          "end_ref": "05028018",
          "end_ref_usfm": "DEU 28:18"
        },
        {
          "start_ref": "05028033",
          "start_ref_usfm": "DEU 28:33",
          "end_ref": "05028033",
          "end_ref_usfm": "DEU 28:33"
        },
        {
          "start_ref": "05028042",
          "start_ref_usfm": "DEU 28:42",
          "end_ref": "05028042",
          "end_ref_usfm": "DEU 28:42"
        },
        {
          "start_ref": "05028051",
          "start_ref_usfm": "DEU 28:51",
          "end_ref": "05028051",
          "end_ref_usfm": "DEU 28:51"
        },
        {
          "start_ref": "05030009",
          "start_ref_usfm": "DEU 30:9",
          "end_ref": "05030009",
          "end_ref_usfm": "DEU 30:9"
        },
        {
          "start_ref": "16009036",
          "start_ref_usfm": "NEH 9:36",
          "end_ref": "16009036",
          "end_ref_usfm": "NEH 9:36"
        },
        {
          "start_ref": "19072016",
          "start_ref_usfm": "PSA 72:16",
          "end_ref": "19072016",
          "end_ref_usfm": "PSA 72:16"
        },
        {
          "start_ref": "19105035",
          "start_ref_usfm": "PSA 105:35",
          "end_ref": "19105035",
          "end_ref_usfm": "PSA 105:35"
        },
        {
          "start_ref": "19107034",
          "start_ref_usfm": "PSA 107:34",
          "end_ref": "19107034",
          "end_ref_usfm": "PSA 107:34"
        },
        {
          "start_ref": "23004002",
          "start_ref_usfm": "ISA 4:2",
          "end_ref": "23004002",
          "end_ref_usfm": "ISA 4:2"
        },
        {
          "start_ref": "24002007",
          "start_ref_usfm": "JER 2:7",
          "end_ref": "24002007",
          "end_ref_usfm": "JER 2:7"
        },
        {
          "start_ref": "24029005",
          "start_ref_usfm": "JER 29:5",
          "end_ref": "24029005",
          "end_ref_usfm": "JER 29:5"
        },
        {
          "start_ref": "24029028",
          "start_ref_usfm": "JER 29:28",
          "end_ref": "24029028",
          "end_ref_usfm": "JER 29:28"
        },
        {
          "start_ref": "26004009",
          "start_ref_usfm": "EZK 4:9",
          "end_ref": "26004009",
          "end_ref_usfm": "EZK 4:9"
        },
        {
          "start_ref": "39003011",
          "start_ref_usfm": "MAL 3:11",
          "end_ref": "39003011",
          "end_ref_usfm": "MAL 3:11"
        }
      ],
      "resource": []
    }
  }
]