[
  {
    "content_id": 292986,
    "reference_id": 2139,
    "version": "1.0.0",
    "title": "Núi Cháy",
    "media_type": "Image",
    "index_reference": "núi cháy",
    "language": "vie",
    "content": "<h3>Image Content</h3>\n<block>\n<p><img src='https://cdn.aquifer.bible/aquifer-content/resources/Media/WEB-0094_burning_mountain.jpg' alt='Image' /></p>\n<p><a href='https://cdn.aquifer.bible/aquifer-content/resources/Media/WEB-0094_burning_mountain.jpg'>link</a></p>\n</block>",
    "associations": {
      "passage": [
        {
          "start_ref": "02019018",
          "start_ref_usfm": "EXO 19:18",
          "end_ref": "02019018",
          "end_ref_usfm": "EXO 19:18"
        },
        {
          "start_ref": "02024017",
          "start_ref_usfm": "EXO 24:17",
          "end_ref": "02024017",
          "end_ref_usfm": "EXO 24:17"
        },
        {
          "start_ref": "05004011",
          "start_ref_usfm": "DEU 4:11",
          "end_ref": "05004011",
          "end_ref_usfm": "DEU 4:11"
        },
        {
          "start_ref": "05005004",
          "start_ref_usfm": "DEU 5:4",
          "end_ref": "05005004",
          "end_ref_usfm": "DEU 5:4"
        },
        {
          "start_ref": "05005005",
          "start_ref_usfm": "DEU 5:5",
          "end_ref": "05005005",
          "end_ref_usfm": "DEU 5:5"
        },
        {
          "start_ref": "05005022",
          "start_ref_usfm": "DEU 5:22",
          "end_ref": "05005022",
          "end_ref_usfm": "DEU 5:22"
        },
        {
          "start_ref": "05005023",
          "start_ref_usfm": "DEU 5:23",
          "end_ref": "05005023",
          "end_ref_usfm": "DEU 5:23"
        },
        {
          "start_ref": "05009010",
          "start_ref_usfm": "DEU 9:10",
          "end_ref": "05009010",
          "end_ref_usfm": "DEU 9:10"
        },
        {
          "start_ref": "05009015",
          "start_ref_usfm": "DEU 9:15",
          "end_ref": "05009015",
          "end_ref_usfm": "DEU 9:15"
        },
        {
          "start_ref": "05009021",
          "start_ref_usfm": "DEU 9:21",
          "end_ref": "05009021",
          "end_ref_usfm": "DEU 9:21"
        },
        {
          "start_ref": "05010004",
          "start_ref_usfm": "DEU 10:4",
          "end_ref": "05010004",
          "end_ref_usfm": "DEU 10:4"
        },
        {
          "start_ref": "05032022",
          "start_ref_usfm": "DEU 32:22",
          "end_ref": "05032022",
          "end_ref_usfm": "DEU 32:22"
        },
        {
          "start_ref": "19083015",
          "start_ref_usfm": "PSA 83:15",
          "end_ref": "19083015",
          "end_ref_usfm": "PSA 83:15"
        },
        {
          "start_ref": "66008008",
          "start_ref_usfm": "REV 8:8",
          "end_ref": "66008008",
          "end_ref_usfm": "REV 8:8"
        }
      ],
      "resource": []
    }
  }
]