[
  {
    "content_id": 295101,
    "reference_id": 2388,
    "title": "地毯",
    "media_type": "Image",
    "index_reference": "地毯",
    "language": "zhs",
    "content": "<h3>Image Content</h3>\n<block>\n<p><img src='https://cdn.aquifer.bible/aquifer-content/resources/Media/WEB-0489_carpet.jpg' alt='Image' /></p>\n<p><a href='https://cdn.aquifer.bible/aquifer-content/resources/Media/WEB-0489_carpet.jpg'>link</a></p>\n</block>",
    "associations": {
      "passage": [
        {
          "start_ref": "07004018",
          "start_ref_usfm": "JDG 4:18",
          "end_ref": "07004018",
          "end_ref_usfm": "JDG 4:18"
        },
        {
          "start_ref": "07005010",
          "start_ref_usfm": "JDG 5:10",
          "end_ref": "07005010",
          "end_ref_usfm": "JDG 5:10"
        },
        {
          "start_ref": "23021005",
          "start_ref_usfm": "ISA 21:5",
          "end_ref": "23021005",
          "end_ref_usfm": "ISA 21:5"
        },
        {
          "start_ref": "26027024",
          "start_ref_usfm": "EZK 27:24",
          "end_ref": "26027024",
          "end_ref_usfm": "EZK 27:24"
        }
      ],
      "resource": []
    }
  }
]