[
  {
    "content_id": 294260,
    "reference_id": 1547,
    "version": "1.0.0",
    "title": "野牛",
    "media_type": "Image",
    "index_reference": "野牛",
    "language": "zhs",
    "content": "<h3>Image Content</h3>\n<block>\n<p><img src='https://cdn.aquifer.bible/aquifer-content/resources/Media/WEB-0073_bison.jpg' alt='Image' /></p>\n<p><a href='https://cdn.aquifer.bible/aquifer-content/resources/Media/WEB-0073_bison.jpg'>link</a></p>\n</block>",
    "associations": {
      "passage": [
        {
          "start_ref": "04023022",
          "start_ref_usfm": "NUM 23:22",
          "end_ref": "04023022",
          "end_ref_usfm": "NUM 23:22"
        },
        {
          "start_ref": "04024008",
          "start_ref_usfm": "NUM 24:8",
          "end_ref": "04024008",
          "end_ref_usfm": "NUM 24:8"
        },
        {
          "start_ref": "05033017",
          "start_ref_usfm": "DEU 33:17",
          "end_ref": "05033017",
          "end_ref_usfm": "DEU 33:17"
        },
        {
          "start_ref": "18039009",
          "start_ref_usfm": "JOB 39:9",
          "end_ref": "18039009",
          "end_ref_usfm": "JOB 39:9"
        },
        {
          "start_ref": "18039010",
          "start_ref_usfm": "JOB 39:10",
          "end_ref": "18039010",
          "end_ref_usfm": "JOB 39:10"
        },
        {
          "start_ref": "19022022",
          "start_ref_usfm": "PSA 22:22",
          "end_ref": "19022022",
          "end_ref_usfm": "PSA 22:22"
        },
        {
          "start_ref": "19029006",
          "start_ref_usfm": "PSA 29:6",
          "end_ref": "19029006",
          "end_ref_usfm": "PSA 29:6"
        },
        {
          "start_ref": "19092011",
          "start_ref_usfm": "PSA 92:11",
          "end_ref": "19092011",
          "end_ref_usfm": "PSA 92:11"
        },
        {
          "start_ref": "23034007",
          "start_ref_usfm": "ISA 34:7",
          "end_ref": "23034007",
          "end_ref_usfm": "ISA 34:7"
        }
      ],
      "resource": []
    }
  }
]